LICENSE
MANIFEST.in
README.md
setup.cfg
setup.py
docassemble/__init__.py
docassemble.LAWVRentersRightsWestVirginia.egg-info/PKG-INFO
docassemble.LAWVRentersRightsWestVirginia.egg-info/SOURCES.txt
docassemble.LAWVRentersRightsWestVirginia.egg-info/dependency_links.txt
docassemble.LAWVRentersRightsWestVirginia.egg-info/namespace_packages.txt
docassemble.LAWVRentersRightsWestVirginia.egg-info/not-zip-safe
docassemble.LAWVRentersRightsWestVirginia.egg-info/requires.txt
docassemble.LAWVRentersRightsWestVirginia.egg-info/top_level.txt
docassemble/LAWVRentersRightsWestVirginia/__init__.py
docassemble/LAWVRentersRightsWestVirginia/data/questions/informal_hearing_request.yml
docassemble/LAWVRentersRightsWestVirginia/data/questions/petition_for_appeal.yml
docassemble/LAWVRentersRightsWestVirginia/data/questions/return_of_security_deposit.yml
docassemble/LAWVRentersRightsWestVirginia/data/questions/return_personal_property.yml
docassemble/LAWVRentersRightsWestVirginia/data/questions/warranty_of_habitability.yml
docassemble/LAWVRentersRightsWestVirginia/data/questions/wrongful_occ_answer.yml
docassemble/LAWVRentersRightsWestVirginia/data/sources/README.md
docassemble/LAWVRentersRightsWestVirginia/data/static/README.md
docassemble/LAWVRentersRightsWestVirginia/data/static/as_is_paper.png
docassemble/LAWVRentersRightsWestVirginia/data/static/bill.png
docassemble/LAWVRentersRightsWestVirginia/data/static/calendar.png
docassemble/LAWVRentersRightsWestVirginia/data/static/civil_judgment_order_rental.png
docassemble/LAWVRentersRightsWestVirginia/data/static/clean_room.png
docassemble/LAWVRentersRightsWestVirginia/data/static/code.png
docassemble/LAWVRentersRightsWestVirginia/data/static/compilation.jpg
docassemble/LAWVRentersRightsWestVirginia/data/static/contact.png
docassemble/LAWVRentersRightsWestVirginia/data/static/cotenant.png
docassemble/LAWVRentersRightsWestVirginia/data/static/factory_home.jpg
docassemble/LAWVRentersRightsWestVirginia/data/static/hammer.png
docassemble/LAWVRentersRightsWestVirginia/data/static/house.png
docassemble/LAWVRentersRightsWestVirginia/data/static/icon_form.png
docassemble/LAWVRentersRightsWestVirginia/data/static/icon_time.png
docassemble/LAWVRentersRightsWestVirginia/data/static/mailbox.png
docassemble/LAWVRentersRightsWestVirginia/data/static/move_out.png
docassemble/LAWVRentersRightsWestVirginia/data/static/multi_icons.png
